fishualize/__init__.py
fishualize/fish_functions.py
fishualize/fishualize.py
fishualize/data/fishcolors.csv
fishualize-0.1.0.dist-info/LICENSE
fishualize-0.1.0.dist-info/METADATA
fishualize-0.1.0.dist-info/WHEEL
fishualize-0.1.0.dist-info/top_level.txt
fishualize-0.1.0.dist-info/RECORD
