Metadata-Version: 2.1
Name: fishualize
Version: 0.1.0
Summary: Python version of the fishualize package
Home-page: https://github.com/DoriMG/py_fishualize
Author: Dori Grijseels
Author-email: dgrijseels@outlook.com
License: UNKNOWN
Platform: UNKNOWN
Classifier: Programming Language :: Python :: 3
Classifier: License :: OSI Approved :: GNU General Public License v3 (GPLv3)
Classifier: Operating System :: OS Independent
Requires-Python: >=3.6
Requires-Dist: pandas (>=0.19.0)
Requires-Dist: numpy (>=1.13.0)
Requires-Dist: matplotlib (>=2.0.0)
